<?xml version="1.0" encoding="utf-8" ?>
<dwsync>
<file name="blank.gif" server="hms.designnxt.com//public_html/" local="128496388200000000" remote="129944443200000000" Dst="0" />
<file name="border_bit.jpg" server="hms.designnxt.com//public_html/" local="129100985820000000" remote="129944443200000000" Dst="0" />
<file name="cal_th_repeat.jpg" server="hms.designnxt.com//public_html/" local="129103475320000000" remote="129944443200000000" Dst="0" />
<file name="cal_top_bg.jpg" server="hms.designnxt.com//public_html/" local="129103478240000000" remote="129944443200000000" Dst="0" />
<file name="cal_top_repeat.jpg" server="hms.designnxt.com//public_html/" local="129103480120000000" remote="129944443200000000" Dst="0" />
<file name="checkbox.gif" server="hms.designnxt.com//public_html/" local="129103376360000000" remote="129944443200000000" Dst="0" />
<file name="content_repeat.jpg" server="hms.designnxt.com//public_html/" local="129100979420000000" remote="129944443800000000" Dst="0" />
<file name="corner_bottom_left.jpg" server="hms.designnxt.com//public_html/" local="129100981460000000" remote="129944443800000000" Dst="0" />
<file name="corner_bottom_right.jpg" server="hms.designnxt.com//public_html/" local="129100981460000000" remote="129944443800000000" Dst="0" />
<file name="corner_top_left.jpg" server="hms.designnxt.com//public_html/" local="129100981460000000" remote="129944443800000000" Dst="0" />
<file name="corner_top_right.jpg" server="hms.designnxt.com//public_html/" local="129100981460000000" remote="129944443800000000" Dst="0" />
<file name="icon_idlogo.jpg" server="hms.designnxt.com//public_html/" local="129098267540000000" remote="129944443800000000" Dst="0" />
<file name="logo.png" server="hms.designnxt.com//public_html/" local="129100128580000000" remote="129944443800000000" Dst="0" />
<file name="side_shadowleft.jpg" server="hms.designnxt.com//public_html/" local="129098275440000000" remote="129944443800000000" Dst="0" />
<file name="side_shadowright.jpg" server="hms.designnxt.com//public_html/" local="129098275440000000" remote="129944443800000000" Dst="0" />
<file name="top_bg.jpg" server="hms.designnxt.com//public_html/" local="129100129240000000" remote="129944443800000000" Dst="0" />
<file name="top_search_btn.gif" server="hms.designnxt.com//public_html/" local="129098272100000000" remote="129944443800000000" Dst="0" />
<file name="top_search_inp.gif" server="hms.designnxt.com//public_html/" local="129100137500000000" remote="129944443800000000" Dst="0" />
<file name="top_search_select.gif" server="hms.designnxt.com//public_html/" local="129100137420000000" remote="129944443800000000" Dst="0" />
<file name="year_next.gif" server="hms.designnxt.com//public_html/" local="129103482440000000" remote="129944443800000000" Dst="0" />
<file name="year_prev.gif" server="hms.designnxt.com//public_html/" local="129103482600000000" remote="129944443800000000" Dst="0" />
</dwsync>